setup.py
categorical/__init__.py
categorical/cat.py
categorical.egg-info/PKG-INFO
categorical.egg-info/SOURCES.txt
categorical.egg-info/dependency_links.txt
categorical.egg-info/requires.txt
categorical.egg-info/top_level.txt