Metadata-Version: 1.1
Name: categorical
Version: 0.1.1
Summary: Fast on-demand sampling from categorical distributions
Home-page: https://github.com/enewe101/categorical
Author: Edward Newell
Author-email: edward.newell@gmail.com
License: MIT
Keywords: sample sampler sampling categorical multinomial discrete distribution statistics probability random
Platform: UNKNOWN
Classifier: Development Status :: 3 - Alpha
Classifier: Intended Audience :: Developers
Classifier: Topic :: Software Development :: Build Tools
Classifier: License :: OSI Approved :: MIT License
Classifier: Programming Language :: Python :: 2.7
